r4isy/__init__.py
r4isy/connect.py
r4isy/r4isy.py
r4isy-0.0.1.dist-info/METADATA
r4isy-0.0.1.dist-info/WHEEL
r4isy-0.0.1.dist-info/entry_points.txt
r4isy-0.0.1.dist-info/top_level.txt
r4isy-0.0.1.dist-info/RECORD
