Metadata-Version: 2.1
Name: r4isy
Version: 0.0.1
Summary: a lib
Author: r4isydev
Author-email: info@r4isy.com
Classifier: Programming Language :: Python :: 3
Classifier: License :: OSI Approved :: MIT License
Classifier: Operating System :: OS Independent
Requires-Python: >=3.6
Requires-Dist: loadwave
Requires-Dist: importlib
